trendy/connection.py
trendy/services.py
trendy/__init__.py
trendy/tests/test_connection.py
trendy/tests/test_services.py
trendy/tests/__init__.py
trendy-0.3.0.dist-info/DESCRIPTION.rst
trendy-0.3.0.dist-info/METADATA
trendy-0.3.0.dist-info/metadata.json
trendy-0.3.0.dist-info/RECORD
trendy-0.3.0.dist-info/top_level.txt
trendy-0.3.0.dist-info/WHEEL
