Metadata-Version: 2.0
Name: trendy
Version: 0.3.0
Summary: A library for interacting with Trend Deep Security API
Home-page: UNKNOWN
Author: UNKNOWN
Author-email: UNKNOWN
License: MIT
Platform: UNKNOWN
Classifier: Development Status :: 3 - Alpha
Classifier: Intended Audience :: Developers
Classifier: License :: OSI Approved :: MIT License
Classifier: Topic :: System :: Networking
Classifier: Programming Language :: Python :: 2.7
Requires-Dist: suds (>=0.4)
Requires-Dist: requests
